main.py
source_serpstat/__init__.py
source_serpstat/manifest.yaml
source_serpstat/run.py
source_serpstat/source.py
airbyte_source_serpstat-0.1.11.dist-info/METADATA
airbyte_source_serpstat-0.1.11.dist-info/WHEEL
airbyte_source_serpstat-0.1.11.dist-info/entry_points.txt
airbyte_source_serpstat-0.1.11.dist-info/RECORD
